setup.py
txt2mobi/__init__.py
txt2mobi/exceptions.py
txt2mobi/main.py
txt2mobi/scaffold.py
txt2mobi/txt2html.py
txt2mobi/utilities.py
txt2mobi.egg-info/PKG-INFO
txt2mobi.egg-info/SOURCES.txt
txt2mobi.egg-info/dependency_links.txt
txt2mobi.egg-info/entry_points.txt
txt2mobi.egg-info/not-zip-safe
txt2mobi.egg-info/requires.txt
txt2mobi.egg-info/top_level.txt