Metadata-Version: 1.0
Name: txt2mobi
Version: 0.0.1
Summary: Convert Chinese-Novel txt book to kindle .mobi file
Home-page: https://github.com/ipconfiger/txt2mobi
Author: Alexander.Li
Author-email: superpowerlee@gmail.com
License: GNU GENERAL PUBLIC LICENSE
Platform: UNKNOWN
